MANIFEST.in
README.md
setup.cfg
setup.py
alapage/__init__.py
alapage/admin.py
alapage/apps.py
alapage/conf.py
alapage/forms.py
alapage/models.py
alapage/tests.py
alapage/urls.py
alapage/utils.py
alapage/views.py
alapage/locale/fr/LC_MESSAGES/django.mo
alapage/locale/fr/LC_MESSAGES/django.po
alapage/management/__init__.py
alapage/management/conf.py
alapage/management/__pycache__/__init__.cpython-35.pyc
alapage/management/__pycache__/__init__.cpython-36.pyc
alapage/management/commands/__init__.py
alapage/management/commands/create_homepage.py
alapage/management/commands/create_page.py
alapage/management/commands/populate_page.py
alapage/management/commands/__pycache__/__init__.cpython-35.pyc
alapage/management/commands/__pycache__/__init__.cpython-36.pyc
alapage/management/commands/__pycache__/create_homepage.cpython-35.pyc
alapage/management/commands/__pycache__/create_homepage.cpython-36.pyc
alapage/management/commands/__pycache__/create_page.cpython-35.pyc
alapage/migrations/0001_initial.py
alapage/migrations/__init__.py
alapage/migrations/__pycache__/0001_initial.cpython-35.pyc
alapage/migrations/__pycache__/0001_initial.cpython-36.pyc
alapage/migrations/__pycache__/0002_page_slideshow_group.cpython-35.pyc
alapage/migrations/__pycache__/__init__.cpython-35.pyc
alapage/migrations/__pycache__/__init__.cpython-36.pyc
alapage/static/alapage/tree.css
alapage/static/ckeditor/ckeditor/config.js
alapage/templates/admin/alapage/page/change_form.html
alapage/templates/admin/alapage/page/change_list.html
alapage/templates/alapage/blank.html
alapage/templates/alapage/default.html
alapage/templates/alapage/fullwidth.html
alapage/templates/alapage/map.html
alapage/templates/alapage/smooth.html
alapage/templates/alapage/inlines/edit_btn.html
alapage/templates/alapage/layouts/bottom.html
alapage/templates/alapage/layouts/smooth-md/top.html
alapage/templates/alapage/layouts/xs-12/top.html
alapage/templates/alapage/wizard/index.html
django_alapage.egg-info/PKG-INFO
django_alapage.egg-info/SOURCES.txt
django_alapage.egg-info/dependency_links.txt
django_alapage.egg-info/not-zip-safe
django_alapage.egg-info/requires.txt
django_alapage.egg-info/top_level.txt