Metadata-Version: 1.1
Name: django-alapage
Version: 0.8
Summary: Page management app for Django
Home-page: https://github.com/synw/django-alapage
Author: synw
Author-email: synwe@yahoo.com
License: UNKNOWN
Download-URL: https://github.com/synw/django-alapage/releases/tag/0.8
Keywords: django,page management
Platform: UNKNOWN
Classifier: Development Status :: 4 - Beta
Classifier: Framework :: Django :: 1.11
Classifier: Intended Audience :: Developers
Classifier: License :: OSI Approved :: MIT License
Classifier: Programming Language :: Python :: 3.6
